led/__init__.py
led/__version__.py
led/api.py
led/cli.py
led/config.py
led/constants.py
led/core.py
led/error.py
led/log.py
led/show.py
led/utils.py
led-0.0.2.dist-info/LICENSE
led-0.0.2.dist-info/METADATA
led-0.0.2.dist-info/WHEEL
led-0.0.2.dist-info/entry_points.txt
led-0.0.2.dist-info/top_level.txt
led-0.0.2.dist-info/RECORD
